netauto_utils/__init__.py
netauto_utils/cisco_show.py
netauto_utils/command_sender.py
netauto_utils/data_converter.py
netauto_utils/ip_address.py
netauto_utils-0.1.0.dist-info/WHEEL
netauto_utils-0.1.0.dist-info/METADATA
netauto_utils-0.1.0.dist-info/RECORD
