Metadata-Version: 2.1
Name: netauto-utils
Version: 0.1.0
Summary: 
Author: ns03444
Requires-Python: >=3.10,<4.0
Classifier: Programming Language :: Python :: 3
Classifier: Programming Language :: Python :: 3.10
Requires-Dist: netaddr (>=0.8.0,<0.9.0)
Requires-Dist: netmiko (>=4.1.2,<5.0.0)
Requires-Dist: paramiko (>=2.12.0,<3.0.0)
Requires-Dist: rich (>=13.0.1,<14.0.0)
